Workbook

Sheet Notes
A1: QuinStreet LBO - purpose and method
A2: Tests whether Ridgeline Capital (fictional $2B fund) could buy QuinStreet (QNST) and earn its target return, and solves for the maximum price it could pay.
A3: QuinStreet was the top-ranked eligible company in the screen (docs/scoring_methodology.md).
A5: Key modeling choices
A6: 1. EBITDA is strict (operating income + D&A). Stock-based compensation is treated as a real cost, assumed replaced by cash pay after the buyout.
A7: 2. Lenders may add back stock-based compensation when sizing debt (switch on Inputs). This raises debt and risk.
A8: 3. Capex includes capitalized internal software development ($10.9M in FY2026), which the screen's CapEx metric excluded.
A9: 4. Interest is charged on beginning-of-year debt to avoid a circular reference.
A10: 5. No dividends during the hold, so IRR = MOIC^(1/years) - 1.
A11: 6. Exit at today's market EV/EBITDA, with no control premium at exit.
A13: Limitations
A14: Annual model; simplified tax (no use of tax losses); one senior loan; illustrative interest rate; base-case operating assumptions are judgments, not forecasts.
A15: Share price is a single day's close (2026-10-23). Not investment advice.

Sheet Inputs
A1: QuinStreet (QNST) LBO - Inputs
A2: $ millions unless stated. Blue = hard-coded input; black = formula; yellow fill = key assumption to flex.
A4: Item | B4: Value | C4: Unit | D4: Source / rationale
A5: Market data
A6: Current share price | B6: 16.52 | C6: $ / share | D6: Nasdaq.com historical quotes, close 2026-10-23 (data/raw/share_prices.csv)
A7: Shares outstanding | B7: 57.1 | C7: millions | D7: 10-K FY2026 cover page, shares as of 2026-08-21 (SEC dei data)
A8: Offer premium to current price | B8: 0.3 | C8: % | D8: Assumption: typical take-private premium of 20-40%
A10: FY2026 actuals (fiscal year ended June 30, 2026)
A11: Revenue | B11: 1293.7 | C11: $M | D11: QNST 10-K FY2026, income statement
A12: EBITDA (strict: operating income + D&A) | B12: 60.6 | C12: $M | D12: Calculated in src/metrics.py; SBC treated as a real cost
A13: Depreciation and amortization | B13: 25.2 | C13: $M | D13: QNST 10-K FY2026, cash flow statement
A14: Stock-based compensation | B14: 37.4 | C14: $M | D14: QNST 10-K FY2026, cash flow statement
A15: Capital expenditures | B15: 3.4 | C15: $M | D15: QNST 10-K FY2026, cash flow statement
A16: Capitalized internal software development | B16: 10.9 | C16: $M | D16: QNST 10-K FY2026, cash flow statement (treated as capex in this model)
A17: Cash and cash equivalents | B17: 128.3 | C17: $M | D17: QNST 10-K FY2026, balance sheet
A18: Existing debt (revolver borrowings) | B18: 70 | C18: $M | D18: QNST 10-K FY2026; repaid at closing
A20: Transaction and financing assumptions
A21: Minimum operating cash kept in the business | B21: 30 | C21: $M | D21: Assumption
A22: Transaction and financing fees | B22: 0.03 | C22: % of purchase equity | D22: Assumption
A23: Lenders add back SBC? (1 = yes, 0 = no) | B23: 1 | C23: switch | D23: Assumption: market practice is to lend on adjusted EBITDA
A24: Senior term loan | B24: 4.5 | C24: x lending EBITDA | D24: Assumption: typical for a mid-sized services business
A25: Interest rate on senior debt | B25: 0.085 | C25: % per year | D25: Assumption (illustrative base rate + spread)
A26: Mandatory amortization | B26: 0.01 | C26: % of original loan / year | D26: Assumption: typical term loan
A27: Cash sweep | B27: 1 | C27: % of excess cash used to repay debt | D27: Assumption
A28: Tax rate | B28: 0.25 | C28: % | D28: Same assumption as the screen (mandate, section 7)
A29: Ridgeline maximum equity per deal | B29: 330 | C29: $M | D29: Mandate, section 1 ($2B fund, 6-10 deals)
A30: Target IRR | B30: 0.2 | C30: % per year | D30: Assumption: common PE return hurdle
A32: Operating assumptions (FY2027-FY2031, base case)
A33: Revenue growth per year | B33: 0.08 | C33: % | D33: Assumption: organic growth well below the 30.6% CAGR, which was partly acquired
A34: EBITDA margin reached in FY2031 (strict) | B34: 0.06 | C34: % | D34: Assumption: modest improvement from 4.7% (value-creation case)
A35: D&A | B35: =B13/B11 -> 0.019479014 | C35: % of revenue | D35: Held at FY2026 level
A36: Capex incl. capitalized software | B36: =(B15+B16)/B11 -> 0.011053567 | C36: % of revenue | D36: Held at FY2026 level
A37: Change in working capital | B37: 0.05 | C37: % of revenue increase | D37: Assumption
A38: Exit multiple | B38: 14.6 | C38: x EBITDA (strict) | D38: Assumption: today's market multiple (Model row 18), no control premium at exit

Sheet Model
A1: QuinStreet (QNST) LBO - Model
A2: $ millions unless stated. Green = link to Inputs; black = formula. Every value traces to the Inputs sheet.
A4: A. Purchase price
A5: Current share price ($) | B5: =Inputs!$B$6 -> 16.52
A6: Offer premium | B6: =Inputs!$B$8 -> 0.3
A7: Offer price per share ($) | B7: =B5*(1+B6) -> 21.476
A8: Shares outstanding (millions) | B8: =Inputs!$B$7 -> 57.1
A9: Offer equity value | B9: =B7*B8 -> 1226.2796
A10: Plus: existing debt | B10: =Inputs!$B$18 -> 70
A11: Less: cash | B11: =Inputs!$B$17 -> 128.3
A12: Entry enterprise value | B12: =B9+B10-B11 -> 1167.9796
A13: FY2026 EBITDA (strict) | B13: =Inputs!$B$12 -> 60.6
A14: Entry EV / EBITDA (strict) | B14: =B12/B13 -> 19.273591
A15: Lending EBITDA (strict + SBC if lenders add it back) | B15: =Inputs!$B$12+Inputs!$B$23*Inputs!$B$14 -> 98
A16: Entry EV / lending EBITDA | B16: =B12/B15 -> 11.918159
A17: Memo: current market enterprise value (no premium) | B17: =B5*B8+B10-B11 -> 884.992
A18: Memo: current market EV / EBITDA (strict) | B18: =B17/B13 -> 14.603828
A20: B. Sources and uses at closing
A21: Uses
A22: Purchase of equity | B22: =B9 -> 1226.2796
A23: Refinance existing debt | B23: =B10 -> 70
A24: Transaction and financing fees | B24: =B9*Inputs!$B$22 -> 36.788388
A25: Total uses | B25: =SUM(B22:B24) -> 1333.068
A26: Sources
A27: Excess cash on the balance sheet | B27: =MAX(0,B11-Inputs!$B$21) -> 98.3
A28: Senior term loan | B28: =B15*Inputs!$B$24 -> 441
A29: Ridgeline equity | B29: =B25-B27-B28 -> 793.76799
A30: Total sources | B30: =SUM(B27:B29) -> 1333.068
A31: Check: sources - uses (must be 0) | B31: =B30-B25 -> 0
A32: Ridgeline maximum equity per deal | B32: =Inputs!$B$29 -> 330
A33: Equity within Ridgeline's limit? | B33: =IF(B29<=B32,"YES","NO") -> NO
A34: Senior debt / FY2026 EBITDA (strict) | B34: =B28/B13 -> 7.2772277
A36: C. Operating projections (fiscal years end June 30)
A37: Fiscal year | C37: FY2026A | D37: FY2027E | E37: FY2028E | F37: FY2029E | G37: FY2030E | H37: FY2031E
A38: Years since closing | C38: 0 | D38: =C38+1 -> 1 | E38: =D38+1 -> 2 | F38: =E38+1 -> 3 | G38: =F38+1 -> 4 | H38: =G38+1 -> 5
A39: Revenue | C39: =Inputs!$B$11 -> 1293.7 | D39: =C39*(1+Inputs!$B$33) -> 1397.196 | E39: =D39*(1+Inputs!$B$33) -> 1508.9717 | F39: =E39*(1+Inputs!$B$33) -> 1629.6894 | G39: =F39*(1+Inputs!$B$33) -> 1760.0646 | H39: =G39*(1+Inputs!$B$33) -> 1900.8697
A40: Revenue growth | D40: =D39/C39-1 -> 0.08 | E40: =E39/D39-1 -> 0.08 | F40: =F39/E39-1 -> 0.08 | G40: =G39/F39-1 -> 0.08 | H40: =H39/G39-1 -> 0.08
A41: EBITDA margin | C41: =C42/C39 -> 0.04684239 | D41: =$C$41+(Inputs!$B$34-$C$41)*D38/$H$38 -> 0.049473912 | E41: =$C$41+(Inputs!$B$34-$C$41)*E38/$H$38 -> 0.052105434 | F41: =$C$41+(Inputs!$B$34-$C$41)*F38/$H$38 -> 0.054736956 | G41: =$C$41+(Inputs!$B$34-$C$41)*G38/$H$38 -> 0.057368478 | H41: =$C$41+(Inputs!$B$34-$C$41)*H38/$H$38 -> 0.06
A42: EBITDA (strict) | C42: =Inputs!$B$12 -> 60.6 | D42: =D39*D41 -> 69.124752 | E42: =E39*E41 -> 78.625624 | F42: =F39*F41 -> 89.204238 | G42: =G39*G41 -> 100.97223 | H42: =H39*H41 -> 114.05218
A43: Depreciation and amortization | C43: =Inputs!$B$13 -> 25.2 | D43: =D39*Inputs!$B$35 -> 27.216 | E43: =E39*Inputs!$B$35 -> 29.39328 | F43: =F39*Inputs!$B$35 -> 31.744742 | G43: =G39*Inputs!$B$35 -> 34.284322 | H43: =H39*Inputs!$B$35 -> 37.027068
A44: EBIT (operating income) | C44: =C42-C43 -> 35.4 | D44: =D42-D43 -> 41.908752 | E44: =E42-E43 -> 49.232344 | F44: =F42-F43 -> 57.459495 | G44: =G42-G43 -> 66.687904 | H44: =H42-H43 -> 77.025116
A45: Interest expense (on beginning debt) | D45: =D53*Inputs!$B$25 -> 37.485 | E45: =E53*Inputs!$B$25 -> 36.642224 | F45: =F53*Inputs!$B$25 -> 35.233981 | G45: =G53*Inputs!$B$25 -> 33.163031 | H45: =H53*Inputs!$B$25 -> 30.319422
A46: Pre-tax income | D46: =D44-D45 -> 4.423752 | E46: =E44-E45 -> 12.590121 | F46: =F44-F45 -> 22.225515 | G46: =G44-G45 -> 33.524872 | H46: =H44-H45 -> 46.705694
A47: Taxes | D47: =MAX(0,D46)*Inputs!$B$28 -> 1.105938 | E47: =MAX(0,E46)*Inputs!$B$28 -> 3.1475301 | F47: =MAX(0,F46)*Inputs!$B$28 -> 5.5563787 | G47: =MAX(0,G46)*Inputs!$B$28 -> 8.3812181 | H47: =MAX(0,H46)*Inputs!$B$28 -> 11.676424
A48: Capex incl. capitalized software | C48: =Inputs!$B$15+Inputs!$B$16 -> 14.3 | D48: =D39*Inputs!$B$36 -> 15.444 | E48: =E39*Inputs!$B$36 -> 16.67952 | F48: =F39*Inputs!$B$36 -> 18.013882 | G48: =G39*Inputs!$B$36 -> 19.454992 | H48: =H39*Inputs!$B$36 -> 21.011391
A49: Increase in working capital | D49: =(D39-C39)*Inputs!$B$37 -> 5.1748 | E49: =(E39-D39)*Inputs!$B$37 -> 5.588784 | F49: =(F39-E39)*Inputs!$B$37 -> 6.0358867 | G49: =(G39-F39)*Inputs!$B$37 -> 6.5187577 | H49: =(H39-G39)*Inputs!$B$37 -> 7.0402583
A50: Cash available for debt repayment | D50: =D42-D47-D48-D49-D45 -> 9.915014 | E50: =E42-E47-E48-E49-E45 -> 16.567566 | F50: =F42-F47-F48-F49-F45 -> 24.36411 | G50: =G42-G47-G48-G49-G45 -> 33.454226 | H50: =H42-H47-H48-H49-H45 -> 44.004689
A52: D. Debt schedule (column C = at closing)
A53: Beginning debt | D53: =C56 -> 441 | E53: =D56 -> 431.08499 | F53: =E56 -> 414.51742 | G53: =F56 -> 390.15331 | H53: =G56 -> 356.69908
A54: Mandatory amortization | D54: =MIN(D53,$B$28*Inputs!$B$26) -> 4.41 | E54: =MIN(E53,$B$28*Inputs!$B$26) -> 4.41 | F54: =MIN(F53,$B$28*Inputs!$B$26) -> 4.41 | G54: =MIN(G53,$B$28*Inputs!$B$26) -> 4.41 | H54: =MIN(H53,$B$28*Inputs!$B$26) -> 4.41
A55: Cash sweep (optional repayment) | D55: =MIN(D53-D54,MAX(0,D50-D54)*Inputs!$B$27) -> 5.505014 | E55: =MIN(E53-E54,MAX(0,E50-E54)*Inputs!$B$27) -> 12.157566 | F55: =MIN(F53-F54,MAX(0,F50-F54)*Inputs!$B$27) -> 19.95411 | G55: =MIN(G53-G54,MAX(0,G50-G54)*Inputs!$B$27) -> 29.044226 | H55: =MIN(H53-H54,MAX(0,H50-H54)*Inputs!$B$27) -> 39.594689
A56: Ending debt | C56: =B28 -> 441 | D56: =D53-D54-D55 -> 431.08499 | E56: =E53-E54-E55 -> 414.51742 | F56: =F53-F54-F55 -> 390.15331 | G56: =G53-G54-G55 -> 356.69908 | H56: =H53-H54-H55 -> 312.69439
A57: Beginning cash | D57: =C58 -> 30 | E57: =D58 -> 30 | F57: =E58 -> 30 | G57: =F58 -> 30 | H57: =G58 -> 30
A58: Ending cash | C58: =Inputs!$B$21 -> 30 | D58: =D57+D50-D54-D55 -> 30 | E58: =E57+E50-E54-E55 -> 30 | F58: =F57+F50-F54-F55 -> 30 | G58: =G57+G50-G54-G55 -> 30 | H58: =H57+H50-H54-H55 -> 30
A59: Net debt (debt - cash) | C59: =C56-C58 -> 411 | D59: =D56-D58 -> 401.08499 | E59: =E56-E58 -> 384.51742 | F59: =F56-F58 -> 360.15331 | G59: =G56-G58 -> 326.69908 | H59: =H56-H58 -> 282.69439
A60: Net debt / EBITDA | C60: =C59/C42 -> 6.7821782 | D60: =D59/D42 -> 5.8023353 | E60: =E59/E42 -> 4.8904848 | F60: =F59/F42 -> 4.0374013 | G60: =G59/G42 -> 3.2355341 | H60: =H59/H42 -> 2.4786408
A62: E. Exit (end of FY2031) and returns
A63: Exit-year EBITDA (FY2031, strict) | B63: =H42 -> 114.05218
A64: Exit multiple (x EBITDA) | B64: =Inputs!$B$38 -> 14.6
A65: Exit enterprise value | B65: =B63*B64 -> 1665.1619
A66: Less: debt at exit | B66: =H56 -> 312.69439
A67: Plus: cash at exit | B67: =H58 -> 30
A68: Exit equity value | B68: =B65-B66+B67 -> 1382.4675
A69: Ridgeline equity invested | B69: =B29 -> 793.76799
A70: MOIC (multiple on invested capital) | B70: =B68/B69 -> 1.7416519
A71: IRR (single entry and exit cash flow: MOIC^(1/years) - 1) | B71: =B70^(1/H38)-1 -> 0.11735781
A72: Target IRR | B72: =Inputs!$B$30 -> 0.2
A73: Meets target IRR? | B73: =IF(B71>=B72,"YES","NO") -> NO
A75: F. Where the return comes from (value creation bridge)
A76: Entry EV / EBITDA (strict) | B76: =B14 -> 19.273591
A77: EBITDA growth [(exit EBITDA - entry EBITDA) x entry multiple] | B77: =(B63-B13)*B76 -> 1030.2155
A78: Multiple change [(exit multiple - entry multiple) x exit EBITDA] | B78: =(B64-B76)*B63 -> -533.03323
A79: Net debt paydown [net debt at close - net debt at exit] | B79: =C59-H59 -> 128.30561
A80: Fees paid at closing | B80: =-B24 -> -36.788388
A81: Total gain to Ridgeline | B81: =SUM(B77:B80) -> 588.6995
A82: Check: total gain - (exit equity - equity invested) (must be 0) | B82: =B81-(B68-B69) -> 0
A84: G. What could Ridgeline pay?
A85: Maximum equity that still earns the target IRR | B85: =B68/(1+B72)^H38 -> 555.58268
A86: Maximum price per share at target IRR ($) | B86: =(B85+B27+B28-B23)/(1+Inputs!$B$22)/B8 -> 17.426125
A87: Maximum price per share within Ridgeline's equity limit ($) | B87: =(B32+B27+B28-B23)/(1+Inputs!$B$22)/B8 -> 13.590533
A88: Maximum price Ridgeline could pay ($) | B88: =MIN(B86,B87) -> 13.590533
A89: Binding constraint | B89: =IF(B86<B87,"Target IRR","Equity limit") -> Equity limit
A90: Premium / (discount) to current share price | B90: =B88/B5-1 -> -0.17732853
A91: Verdict | B91: =IF(B88<B5,"PASS: cannot pay even the current market price",IF(B88<B5*1.2,"MARGINAL: below a typical 20%+ takeover premium","ACTIONABLE: can pay a competitive premium")) -> PASS: cannot pay even the current market price
A93: Note: debt depends on EBITDA, not on the price paid, so exit equity does not change with the offer price. That is why the maximum price can be solved directly, without Goal Seek.
